withpi_utils/__about__.py
withpi_utils/__init__.py
withpi_utils/colab.py
withpi_utils/jobs.py
withpi_utils/question_builders.py
withpi_utils-0.0.12.dist-info/METADATA
withpi_utils-0.0.12.dist-info/WHEEL
withpi_utils-0.0.12.dist-info/licenses/LICENSE
withpi_utils-0.0.12.dist-info/RECORD
