Metadata-Version: 2.4
Name: withpi-utils
Version: 0.0.12
Project-URL: Documentation, https://github.com/withpi/python-utils#readme
Project-URL: Issues, https://github.com/withpi/python-utils/issues
Project-URL: Source, https://github.com/withpi/python-utils
Author-email: Zach Clifford <zach@withpi.ai>
License-Expression: Apache-2.0
License-File: LICENSE
Classifier: Development Status :: 4 - Beta
Classifier: Programming Language :: Python
Classifier: Programming Language :: Python :: 3.8
Classifier: Programming Language :: Python :: 3.9
Classifier: Programming Language :: Python :: 3.10
Classifier: Programming Language :: Python :: 3.11
Classifier: Programming Language :: Python :: 3.12
Classifier: Programming Language :: Python :: Implementation :: CPython
Classifier: Programming Language :: Python :: Implementation :: PyPy
Requires-Python: >=3.8
Requires-Dist: ipython>=7.34.0
Requires-Dist: markdown>=3.7
Requires-Dist: matplotlib>=3.7.5
Requires-Dist: numpy>=1.24.4
Requires-Dist: withpi>=1.24.0
